meshgrid/__init__.py
meshgrid/player.py
meshgrid/examples/rpg.py
meshgrid/examples/tetronimo.py
meshgrid/games/__init__.py
meshgrid/games/square.py
meshgrid/grids/__init__.py
meshgrid/grids/square.py
meshgrid/grids/square_multilayer.py
meshgrid/queueing/__init__.py
meshgrid/queueing/discrete.py
meshgrid/shape/__init__.py
meshgrid/shape/square.py
meshgrid/visualizers/__init__.py
meshgrid/visualizers/notebook.py
meshgrid-0.0.2.dist-info/LICENSE.txt
meshgrid-0.0.2.dist-info/METADATA
meshgrid-0.0.2.dist-info/WHEEL
meshgrid-0.0.2.dist-info/top_level.txt
meshgrid-0.0.2.dist-info/RECORD
