Metadata-Version: 2.1
Name: meshgrid
Version: 0.0.2
Summary: A Jupyter Notebook based game engine for grid-based games
Author: Kyle Horn
Author-email: meshgrid.game@gmail.com
Classifier: Programming Language :: Python :: 3
Classifier: License :: OSI Approved :: MIT License
Classifier: Operating System :: OS Independent
License-File: LICENSE.txt
Requires-Dist: jupyter
Requires-Dist: numpy
Requires-Dist: ipycanvas
